ml_web_inference/__init__.py
ml_web_inference/main.py
ml_web_inference-0.1.3.dist-info/LICENSE
ml_web_inference-0.1.3.dist-info/METADATA
ml_web_inference-0.1.3.dist-info/WHEEL
ml_web_inference-0.1.3.dist-info/top_level.txt
ml_web_inference-0.1.3.dist-info/RECORD
